{
    "created_time": "2024-05-14T05:21:54Z",
    "files": [
        {
            "attachment_folder": "",
            "created_time": "2024-05-14T05:22:18Z",
            "id": "188",
            "modified_time": "2024-05-14T05:23:42Z",
            "name": "每年预算.md",
            "signature": "784285915005777162",
            "tags": [
            ]
        }
    ],
    "folders": [
    ],
    "id": "187",
    "modified_time": "2024-05-14T05:21:54Z",
    "signature": "207324082009330",
    "version": 3
}
